lparchive2epub/__init__.py
lparchive2epub/lib.py
lparchive2epub/main.py
lparchive2epub/style.py
lparchive2epub-1.4.2.dist-info/entry_points.txt
lparchive2epub-1.4.2.dist-info/LICENSE
lparchive2epub-1.4.2.dist-info/METADATA
lparchive2epub-1.4.2.dist-info/WHEEL
lparchive2epub-1.4.2.dist-info/RECORD
