Metadata-Version: 2.1
Name: lparchive2epub
Version: 1.4.2
Summary: 
Home-page: https://github.com/Arwalk/lparchive2epub
Author: Arwalk
Author-email: siragentprovocateurarwalk@gmail.com
Requires-Python: >=3.12,<4.0
Classifier: Programming Language :: Python :: 3
Classifier: Programming Language :: Python :: 3.12
Requires-Dist: aiohttp (>=3.9.5,<4.0.0)
Requires-Dist: aiohttp-client-cache[all] (>=0.13.0,<0.14.0)
Requires-Dist: beautifulsoup4 (>=4.12.2,<5.0.0)
Requires-Dist: ebooklib (>=0.19,<0.20)
Requires-Dist: tqdm (>=4.66.4,<5.0.0)
Project-URL: Repository, https://github.com/Arwalk/lparchive2epub
